LICENSE
README.md
requirements.txt
setup.py
connectivity_tool.egg-info/PKG-INFO
connectivity_tool.egg-info/SOURCES.txt
connectivity_tool.egg-info/dependency_links.txt
connectivity_tool.egg-info/entry_points.txt
connectivity_tool.egg-info/requires.txt
connectivity_tool.egg-info/top_level.txt
connectivity_tool_cli/__init__.py
connectivity_tool_cli/index.py
connectivity_tool_cli/common/__init__.py
connectivity_tool_cli/common/constances.py
connectivity_tool_cli/common/example_generator.py
connectivity_tool_cli/common/input_loader.py
connectivity_tool_cli/common/interfances.py
connectivity_tool_cli/common/logger.py
connectivity_tool_cli/common/utils.py
connectivity_tool_cli/generated_build/__init__.py
connectivity_tool_cli/generated_build/build_info.py
connectivity_tool_cli/models/__init__.py
connectivity_tool_cli/models/conn_result.py
connectivity_tool_cli/models/conn_test_suite.py
connectivity_tool_cli/protocoles/__init__.py
connectivity_tool_cli/protocoles/dns_protocol.py
connectivity_tool_cli/protocoles/protocol.py
connectivity_tool_cli/protocoles/www_protocol.py
connectivity_tool_cli/store/__init__.py
connectivity_tool_cli/store/jsonl_handler.py
connectivity_tool_cli/store/jsonl_store.py
connectivity_tool_cli/store/store_base.py
connectivity_tool_cli/store/store_manager.py
tests/test_unit_global.py
tests/intergration/__init__.py
tests/intergration/test_cli_common.py
tests/intergration/test_cli_direct_test.py
tests/intergration/test_cli_file_suite.py
tests/intergration/test_cli_generate.py
tests/intergration/test_cli_store.py
tests/units/__init__.py
tests/units/common/__init__.py
tests/units/common/test_example_generator.py
tests/units/store/__init__.py
tests/units/store/test_jsonl_handler.py
tests/units/store/test_jsonl_store.py
tests/units/utils/__init__.py