Metadata-Version: 2.1
Name: connectivity_tool
Version: 1.0.13
Summary: A lightweight command-line tool for testing connectivity to web sources over various protocols (HTTPS, DNS, etc).
Home-page: https://github.com/haimkastner/connectivity-tool
Author: Haim Kastner
Author-email: hello@haim-kastner.com
Maintainer: Haim Kastner
Maintainer-email: hello@haim-kastner.com
License: MIT
Keywords: connectivity,http,https,dns,cli
Requires-Python: >=3.10,<4.0
License-File: LICENSE
Requires-Dist: PyYAML==6.0.2
Requires-Dist: unitsnet-py==0.1.140
Requires-Dist: requests~=2.32.3
Requires-Dist: setuptools~=70.0.0
Requires-Dist: validators~=0.34.0
